<country name="Бутан" count="21">
  <point>
    <name>Джакар</name>
    <region>Бумтанг</region>
    <district>Джакар</district>
    <id>381496</id>
  </point>
  <point>
    <name>Вангди-Пходранг</name>
    <region>Вангди-Пходранг</region>
    <district>Вангди-Пходранг</district>
    <id>381514</id>
  </point>
  <point>
    <name>Гаса</name>
    <region>Гаса</region>
    <district>Гаса</district>
    <id>381499</id>
  </point>
  <point>
    <name>Дагана</name>
    <region>Дагана</region>
    <district>Дагана</district>
    <id>381498</id>
  </point>
  <point>
    <name>Жемганг</name>
    <region>Жемганг</region>
    <district>Жемганг</district>
    <id>381515</id>
  </point>
  <point>
    <name>Лхунце</name>
    <region>Лхунце</region>
    <district>Лхунце</district>
    <id>381501</id>
  </point>
  <point>
    <name>Монгар</name>
    <region>Монгар</region>
    <district>Монгар</district>
    <id>381503</id>
  </point>
  <point>
    <name>Паро</name>
    <region>Паро</region>
    <district>Паро</district>
    <id>381504</id>
  </point>
  <point>
    <name>Паро (аэропорт)</name>
    <region>Паро</region>
    <district>Паро (аэропорт)</district>
    <id>508593</id>
  </point>
  <point>
    <name>Пемагацел</name>
    <region>Пемагацел</region>
    <district>Пемагацел</district>
    <id>381505</id>
  </point>
  <point>
    <name>Пунакха</name>
    <region>Пунакха</region>
    <district>Пунакха</district>
    <id>381506</id>
  </point>
  <point>
    <name>Самдруп-Джонкхар</name>
    <region>Самдруп-Джонкхар</region>
    <district>Самдруп-Джонкхар</district>
    <id>381507</id>
  </point>
  <point>
    <name>Самце</name>
    <region>Самце</region>
    <district>Самце</district>
    <id>381508</id>
  </point>
  <point>
    <name>Сарпанг</name>
    <region>Сарпанг</region>
    <district>Сарпанг</district>
    <id>381509</id>
  </point>
  <point>
    <name>Тонгса</name>
    <region>Тонгса</region>
    <district>Тонгса</district>
    <id>381512</id>
  </point>
  <point>
    <name>Трашиганг</name>
    <region>Трашиганг</region>
    <district>Трашиганг</district>
    <id>381510</id>
  </point>
  <point>
    <name>Трашиянгце</name>
    <region>Трашиянгце</region>
    <district>Трашиянгце</district>
    <id>381511</id>
  </point>
  <point>
    <name>Тхимпху</name>
    <region>Тхимпху</region>
    <district>Тхимпху</district>
    <id>337403</id>
  </point>
  <point>
    <name>Хаа</name>
    <region>Хаа</region>
    <district>Хаа</district>
    <id>381500</id>
  </point>
  <point>
    <name>Дампху</name>
    <region>Циранг</region>
    <district>Дампху</district>
    <id>381513</id>
  </point>
  <point>
    <name>Цимашам</name>
    <region>Чукха</region>
    <district>Цимашам</district>
    <id>381497</id>
  </point>
</country>
