<country name="Святой Елены (остров)" count="9">
  <point>
    <name>Аларм-Форест</name>
    <region>Аларм-Форест</region>
    <district>Аларм-Форест</district>
    <id>381673</id>
  </point>
  <point>
    <name>Блю-Хилл</name>
    <region>Блю-Хилл</region>
    <district>Блю-Хилл</district>
    <id>381674</id>
  </point>
  <point>
    <name>Джеймстаун</name>
    <region>Джеймстаун</region>
    <district>Джеймстаун</district>
    <id>151440</id>
  </point>
  <point>
    <name>Левелвуд</name>
    <region>Левелвуд</region>
    <district>Левелвуд</district>
    <id>381676</id>
  </point>
  <point>
    <name>Лонгвуд</name>
    <region>Лонгвуд</region>
    <district>Лонгвуд</district>
    <id>381677</id>
  </point>
  <point>
    <name>о. Вознесения (аэропорт)</name>
    <region>Вознесения (остров)</region>
    <district>о. Вознесения (аэропорт)</district>
    <id>10473</id>
  </point>
  <point>
    <name>Сент-Пол</name>
    <region>Сент-Пол</region>
    <district>Сент-Пол</district>
    <id>381679</id>
  </point>
  <point>
    <name>Сэнди-Бэй</name>
    <region>Сэнди-Бэй</region>
    <district>Сэнди-Бэй</district>
    <id>381678</id>
  </point>
  <point>
    <name>Халф-Три-Холлоу</name>
    <region>Халф-Три-Холлоу</region>
    <district>Халф-Три-Холлоу</district>
    <id>381675</id>
  </point>
</country>
