<country name="Южный Судан" count="13">
  <point>
    <name>Вараб</name>
    <region>Вараб</region>
    <district>Вараб</district>
    <id>212526</id>
  </point>
  <point>
    <name>Кваджок</name>
    <region>Вараб</region>
    <district>Кваджок</district>
    <id>429814</id>
  </point>
  <point>
    <name>Малакал</name>
    <region>Верхний Нил</region>
    <district>Малакал</district>
    <id>10598</id>
  </point>
  <point>
    <name>Ренк</name>
    <region>Верхний Нил</region>
    <district>Ренк</district>
    <id>10593</id>
  </point>
  <point>
    <name>Торит</name>
    <region>Восточная Экватория</region>
    <district>Торит</district>
    <id>212516</id>
  </point>
  <point>
    <name>Бор</name>
    <region>Джонглий</region>
    <district>Бор</district>
    <id>212527</id>
  </point>
  <point>
    <name>Ямбио</name>
    <region>Западная Экватория</region>
    <district>Ямбио</district>
    <id>212517</id>
  </point>
  <point>
    <name>Вау</name>
    <region>Западный Бахр-эль-Газаль</region>
    <district>Вау</district>
    <id>10600</id>
  </point>
  <point>
    <name>Рага</name>
    <region>Западный Бахр-эль-Газаль</region>
    <district>Рага</district>
    <id>10599</id>
  </point>
  <point>
    <name>Румбек</name>
    <region>Озёрный</region>
    <district>Румбек</district>
    <id>212533</id>
  </point>
  <point>
    <name>Авейль</name>
    <region>Северный Бахр-эль-Газаль</region>
    <district>Авейль</district>
    <id>212534</id>
  </point>
  <point>
    <name>Джуба</name>
    <region>Центральная Экватория</region>
    <district>Джуба</district>
    <id>10601</id>
  </point>
  <point>
    <name>Бантио</name>
    <region>Эль-Вахда</region>
    <district>Бантио</district>
    <id>212540</id>
  </point>
</country>
