<country name="Montserrat" count="4">
  <point>
    <name>Plymouth</name>
    <region>Saint Anthony</region>
    <district>Plymouth</district>
    <id>337418</id>
  </point>
  <point>
    <name>Saint Georges</name>
    <region>Saint Georges</region>
    <district>Saint Georges</district>
    <id>381741</id>
  </point>
  <point>
    <name>Saint Peter's</name>
    <region>Saint Peter</region>
    <district>Saint Peter`s</district>
    <id>381740</id>
  </point>
  <point>
    <name>Gerald's / John A. Osborne (airport)</name>
    <region>Saint Peter</region>
    <district>Gerald`s / John A. Osborne (airport)</district>
    <id>508412</id>
  </point>
</country>
