<country name="Vanuatu" count="13">
  <point>
    <name>Lakatoro</name>
    <region>Malampa</region>
    <district>Lakatoro</district>
    <id>348518</id>
  </point>
  <point>
    <name>Lamap (Malekula)</name>
    <region>Malampa</region>
    <district>Lamap (Malekula)</district>
    <id>337832</id>
  </point>
  <point>
    <name>Longana</name>
    <region>Penama</region>
    <district>Longana</district>
    <id>348519</id>
  </point>
  <point>
    <name>Saratamata</name>
    <region>Penama</region>
    <district>Saratamata</district>
    <id>337834</id>
  </point>
  <point>
    <name>Luganville</name>
    <region>Sanma</region>
    <district>Luganville</district>
    <id>348520</id>
  </point>
  <point>
    <name>Santo-Pekoa (airport)</name>
    <region>Sanma</region>
    <district>Santo-Pekoa (airport)</district>
    <id>337833</id>
  </point>
  <point>
    <name>Port Vila</name>
    <region>Shefa</region>
    <district>Port Vila</district>
    <id>337404</id>
  </point>
  <point>
    <name>Port Vila (airport)</name>
    <region>Shefa</region>
    <district>Port Vila (airport)</district>
    <id>337830</id>
  </point>
  <point>
    <name>Port Vila / Bauerfield (airport)</name>
    <region>Shefa</region>
    <district>Port Vila / Bauerfield (airport)</district>
    <id>337831</id>
  </point>
  <point>
    <name>Aneityum</name>
    <region>Tafea</region>
    <district>Aneityum</district>
    <id>337828</id>
  </point>
  <point>
    <name>Isangel</name>
    <region>Tafea</region>
    <district>Isangel</district>
    <id>348521</id>
  </point>
  <point>
    <name>White Grass (airport)</name>
    <region>Tafea</region>
    <district>White Grass (airport)</district>
    <id>337829</id>
  </point>
  <point>
    <name>Sola</name>
    <region>Torba</region>
    <district>Sola</district>
    <id>337835</id>
  </point>
</country>
